dsfr_structure/__init__.py
dsfr_structure/test_runner.py
dsfr_structure/extension/all_extensions.py
dsfr_structure/extension/accordion/__init__.py
dsfr_structure/extension/alert/__init__.py
dsfr_structure/extension/badge/__init__.py
dsfr_structure/extension/blockquote/__init__.py
dsfr_structure/extension/callout/__init__.py
dsfr_structure/extension/card/__init__.py
dsfr_structure/extension/col/__init__.py
dsfr_structure/extension/media/__init__.py
dsfr_structure/extension/notice/__init__.py
dsfr_structure/extension/quote/__init__.py
dsfr_structure/extension/row/__init__.py
dsfr_structure/extension/table/__init__.py
dsfr_structure/extension/tile/__init__.py
dsfr_structure/extension/utils/__init__.py
dsfr_structure/tests/test_accordion.py
dsfr_structure/tests/test_alert.py
dsfr_structure/tests/test_badge.py
dsfr_structure/tests/test_blockquote.py
dsfr_structure/tests/test_callout.py
dsfr_structure/tests/test_card.py
dsfr_structure/tests/test_col.py
dsfr_structure/tests/test_integration_grid.py
dsfr_structure/tests/test_media.py
dsfr_structure/tests/test_notice.py
dsfr_structure/tests/test_quote.py
dsfr_structure/tests/test_row.py
dsfr_structure/tests/test_table.py
dsfr_structure/tests/test_tile.py
dsfr_structure/tests/test_utils.py
dsfr_structure-0.9.0.dist-info/METADATA
dsfr_structure-0.9.0.dist-info/WHEEL
dsfr_structure-0.9.0.dist-info/entry_points.txt
dsfr_structure-0.9.0.dist-info/top_level.txt
dsfr_structure-0.9.0.dist-info/RECORD
