Metadata-Version: 2.4
Name: dsfr_structure
Version: 0.9.0
Author-email: ARTHAUD Geoffrey <geoffrey.artaud@developpement-durable.gouv.fr>
Requires-Python: <4.0,>=3.10
Requires-Dist: mkdocs<2.0.0,>=1.4.3
Requires-Dist: markdown<4.0.0,>=3.5.1
Requires-Dist: pymdown-extensions<11.0,>=10.12
